readtime/__about__.py
readtime/__init__.py
readtime/_compat.py
readtime/api.py
readtime/result.py
readtime/utils.py
readtime-2.0.0.dist-info/AUTHORS
readtime-2.0.0.dist-info/LICENSE
readtime-2.0.0.dist-info/METADATA
readtime-2.0.0.dist-info/WHEEL
readtime-2.0.0.dist-info/top_level.txt
readtime-2.0.0.dist-info/RECORD
